{
  "project_info": {
    "project_number": "830927077117",
    "project_id": "flutter-notifications-d77bc",
    "storage_bucket": "flutter-notifications-d77bc.appspot.com"
  },
  "client": [
    {
      "client_info": {
        "mobilesdk_app_id": "1:830927077117:android:1bbbf672a5cb4601f54894",
        "android_client_info": {
          "package_name": "com.xprtx.flutternotifications"
        }
      },
      "oauth_client": [
        {
          "client_id": "830927077117-os82vuienh1pkqbtsrhlj730d6qklb4h.apps.googleusercontent.com",
          "client_type": 3
        }
      ],
      "api_key": [
        {
          "current_key": "AIzaSyDLwuKDSKOUUqjf1DpzU2UOplOBRvBcwjA"
        }
      ],
      "services": {
        "appinvite_service": {
          "other_platform_oauth_client": [
            {
              "client_id": "830927077117-os82vuienh1pkqbtsrhlj730d6qklb4h.apps.googleusercontent.com",
              "client_type": 3
            }
          ]
        }
      }
    }
  ],
  "configuration_version": "1"
}